DopeShell/__init__.py
DopeShell/client.py
DopeShell/server.py
DopeShell-2.0.1.dist-info/LICENSE
DopeShell-2.0.1.dist-info/METADATA
DopeShell-2.0.1.dist-info/WHEEL
DopeShell-2.0.1.dist-info/entry_points.txt
DopeShell-2.0.1.dist-info/top_level.txt
DopeShell-2.0.1.dist-info/RECORD
