Metadata-Version: 2.1
Name: DopeShell
Version: 2.0.1
Summary: A Python library for creating secure reverse shells with session management and encryption.
Home-page: https://github.com/anonymous300502/DopeShellPyPi
Author: Abhishek Sharma, Manaswi Sharma
Author-email: 170mailmea@gmail.com
Classifier: Programming Language :: Python :: 3
Classifier: License :: OSI Approved :: MIT License
Classifier: Operating System :: OS Independent
Classifier: Development Status :: 4 - Beta
Classifier: Intended Audience :: Developers
Classifier: Topic :: Security
Requires-Python: >=3.7
License-File: LICENSE
Requires-Dist: cryptography>=39.0.0
